setup.py
ut_test_distributions/Binomialdistribution.py
ut_test_distributions/Gaussiandistribution.py
ut_test_distributions/Generaldistribution.py
ut_test_distributions/__init__.py
ut_test_distributions.egg-info/PKG-INFO
ut_test_distributions.egg-info/SOURCES.txt
ut_test_distributions.egg-info/dependency_links.txt
ut_test_distributions.egg-info/not-zip-safe
ut_test_distributions.egg-info/top_level.txt