Metadata-Version: 1.0
Name: ut-test-distributions
Version: 0.1
Summary: Gaussian and Binomial distributions
Home-page: UNKNOWN
Author: Usama Tariq
Author-email: tariqusama95@gmail.com
License: UNKNOWN
Platform: UNKNOWN
